northgravity_utils/BackTest.py
northgravity_utils/DataHandler.py
northgravity_utils/FileHandler.py
northgravity_utils/StatTests.py
northgravity_utils/TaskExecUtils.py
northgravity_utils/__init__.py
northgravity_utils/constants.py
northgravity_utils/utils.py
northgravity_utils-0.1.2.dist-info/LICENSE
northgravity_utils-0.1.2.dist-info/METADATA
northgravity_utils-0.1.2.dist-info/WHEEL
northgravity_utils-0.1.2.dist-info/top_level.txt
northgravity_utils-0.1.2.dist-info/RECORD
