Metadata-Version: 2.1
Name: northgravity_utils
Version: 0.1.2
Summary: Python Utils for NorthGravity platform tasks
Home-page: https://www.northgravity.com/
Author: NorthGravity
Author-email: info@northgravity.com
Keywords: northgravity, utils, ngutils
Classifier: Operating System :: OS Independent
Classifier: License :: OSI Approved :: MIT License
Classifier: Programming Language :: Python :: 3
Classifier: Programming Language :: Python :: 3.6
Classifier: Programming Language :: Python :: 3.7
Classifier: Programming Language :: Python :: 3.8
Classifier: Programming Language :: Python :: 3.9
Classifier: Programming Language :: Python :: 3.10
Classifier: Programming Language :: Python :: 3.11
Requires-Python: >=3.6
License-File: LICENSE
Requires-Dist: northgravity
Requires-Dist: requests
Requires-Dist: urllib3
Requires-Dist: scikit-learn
Requires-Dist: statsmodels
Requires-Dist: fluent-logger
